Metadata-Version: 2.4
Name: truthtrader
Version: 0.1.0
Summary: Cache-first market bar archive: fetch from Polygon (or others), store 1m bars, return any timeframe. No pandas required for callers.
Author: Bryan Clauss
Author-email: bryanclauss@gmail.com
Requires-Python: >=3.11,<4.0
Classifier: Programming Language :: Python :: 3
Classifier: Programming Language :: Python :: 3.11
Classifier: Programming Language :: Python :: 3.12
Classifier: Programming Language :: Python :: 3.13
Classifier: Programming Language :: Python :: 3.14
Requires-Dist: boto3 (>=1.34.0,<2.0.0)
Requires-Dist: fsspec (>=2024.0.0,<2025.0.0)
Requires-Dist: pandas (>=2.2.0,<3.0.0)
Requires-Dist: polygon-api-client (>=1.16.3,<2.0.0)
Requires-Dist: pyarrow (>=15.0.0,<16.0.0)
Requires-Dist: s3fs (>=2024.0.0,<2025.0.0)
